[
    {
        "开课院系": "法学院",
        "课程号": "80661863",
        "课序号": "0",
        "课程名": "知识产权法学",
        "学分": "3",
        "主讲教师": "蒋舸",
        "本科生课容量": "0",
        "本科生课余量": "0",
        "研究生课容量": "80",
        "研究生课余量": "80",
        "上课时间": "3-4(全周),3-3(全周)",
        "选课文字说明": "优先:法律专业学生选课",
        "课程特色": "",
        "年级": "",
        "是否二级选课": "否",
        "实验信息": "",
        "重修是否占容量": "否",
        "是否选课时限制": "",
        "通识选修课组": ""
    },
    {
        "开课院系": "法学院",
        "课程号": "80661944",
        "课序号": "0",
        "课程名": "亚洲国际仲裁",
        "学分": "4",
        "主讲教师": "郑若骅",
        "本科生课容量": "10",
        "本科生课余量": "10",
        "研究生课容量": "40",
        "研究生课余量": "40",
        "上课时间": "(全周)",
        "选课文字说明": "优先:法学院学生选课; 国际仲裁与争端解决项目课程",
        "课程特色": "全外文授课",
        "年级": "",
        "是否二级选课": "否",
        "实验信息": "",
        "重修是否占容量": "否",
        "是否选课时限制": "",
        "通识选修课组": ""
    },
    {
        "开课院系": "法学院",
        "课程号": "80661953",
        "课序号": "0",
        "课程名": "投资仲裁专题研究",
        "学分": "3",
        "主讲教师": "郑若骅",
        "本科生课容量": "10",
        "本科生课余量": "10",
        "研究生课容量": "40",
        "研究生课余量": "40",
        "上课时间": "(全周)",
        "选课文字说明": "",
        "课程特色": "全外文授课",
        "年级": "",
        "是否二级选课": "否",
        "实验信息": "",
        "重修是否占容量": "否",
        "是否选课时限制": "",
        "通识选修课组": ""
    },
    {
        "开课院系": "法学院",
        "课程号": "80662053",
        "课序号": "0",
        "课程名": "中美经济贸易关系中的法律问题",
        "学分": "3",
        "主讲教师": "杨国华",
        "本科生课容量": "15",
        "本科生课余量": "15",
        "研究生课容量": "35",
        "研究生课余量": "35",
        "上课时间": "1-4(全周),1-3(全周)",
        "选课文字说明": "优先:法学院学生选课; 14:20上课",
        "课程特色": "",
        "年级": "",
        "是否二级选课": "否",
        "实验信息": "",
        "重修是否占容量": "否",
        "是否选课时限制": "",
        "通识选修课组": ""
    },
    {
        "开课院系": "法学院",
        "课程号": "80662173",
        "课序号": "0",
        "课程名": "公司法理论与实践",
        "学分": "3",
        "主讲教师": "朱慈蕴",
        "本科生课容量": "15",
        "本科生课余量": "15",
        "研究生课容量": "85",
        "研究生课余量": "85",
        "上课时间": "3-2(后八周),3-6(后八周)",
        "选课文字说明": "优先:法学院法律专业学生选课",
        "课程特色": "",
        "年级": "",
        "是否二级选课": "否",
        "实验信息": "",
        "重修是否占容量": "否",
        "是否选课时限制": "",
        "通识选修课组": ""
    },
    {
        "开课院系": "法学院",
        "课程号": "80662203",
        "课序号": "0",
        "课程名": "计算法学导论：新一代信息技术与法律",
        "学分": "3",
        "主讲教师": "申卫星",
        "本科生课容量": "10",
        "本科生课余量": "10",
        "研究生课容量": "55",
        "研究生课余量": "55",
        "上课时间": "1-4(全周),1-3(全周)",
        "选课文字说明": "优先:法律专业学生选课; 计算法学方向必修;14:20上课",
        "课程特色": "",
        "年级": "",
        "是否二级选课": "否",
        "实验信息": "",
        "重修是否占容量": "否",
        "是否选课时限制": "",
        "通识选修课组": ""
    },
    {
        "开课院系": "法学院",
        "课程号": "80662213",
        "课序号": "0",
        "课程名": "法律方法专题研究",
        "学分": "3",
        "主讲教师": "梁上上",
        "本科生课容量": "5",
        "本科生课余量": "5",
        "研究生课容量": "25",
        "研究生课余量": "25",
        "上课时间": "4-2(全周)",
        "选课文字说明": "优先:法学院硕士学生选课",
        "课程特色": "",
        "年级": "",
        "是否二级选课": "否",
        "实验信息": "",
        "重修是否占容量": "否",
        "是否选课时限制": "",
        "通识选修课组": ""
    },
    {
        "开课院系": "法学院",
        "课程号": "80662222",
        "课序号": "0",
        "课程名": "中国公司法和证券法",
        "学分": "2",
        "主讲教师": "赵晨光",
        "本科生课容量": "0",
        "本科生课余量": "0",
        "研究生课容量": "30",
        "研究生课余量": "30",
        "上课时间": "1-4(前八周),1-3(前八周)",
        "选课文字说明": "限:法律硕士(JM)学生选课；优先:留学生选课",
        "课程特色": "全外文授课",
        "年级": "",
        "是否二级选课": "否",
        "实验信息": "",
        "重修是否占容量": "否",
        "是否选课时限制": "是",
        "通识选修课组": ""
    },
    {
        "开课院系": "法学院",
        "课程号": "80662232",
        "课序号": "0",
        "课程名": "人格权法",
        "学分": "2",
        "主讲教师": "程啸",
        "本科生课容量": "5",
        "本科生课余量": "5",
        "研究生课容量": "25",
        "研究生课余量": "25",
        "上课时间": "2-2(前八周),2-1(前八周)",
        "选课文字说明": "优先:法学院学生选课",
        "课程特色": "",
        "年级": "",
        "是否二级选课": "否",
        "实验信息": "",
        "重修是否占容量": "否",
        "是否选课时限制": "",
        "通识选修课组": ""
    },
    {
        "开课院系": "法学院",
        "课程号": "80662272",
        "课序号": "0",
        "课程名": "跨境并购与国际融资",
        "学分": "2",
        "主讲教师": "王开定",
        "本科生课容量": "10",
        "本科生课余量": "10",
        "研究生课容量": "40",
        "研究生课余量": "40",
        "上课时间": "5-4(前八周),5-3(前八周)",
        "选课文字说明": "优先:法律专业学生选课; 金杜律师事务所行业专家课程",
        "课程特色": "",
        "年级": "",
        "是否二级选课": "否",
        "实验信息": "",
        "重修是否占容量": "否",
        "是否选课时限制": "",
        "通识选修课组": ""
    },
    {
        "开课院系": "法学院",
        "课程号": "80662323",
        "课序号": "0",
        "课程名": "创新法律与政策",
        "学分": "3",
        "主讲教师": "崔国斌",
        "本科生课容量": "10",
        "本科生课余量": "10",
        "研究生课容量": "40",
        "研究生课余量": "40",
        "上课时间": "2-2(全周)",
        "选课文字说明": "优先:法学院学生选课",
        "课程特色": "全外文授课",
        "年级": "",
        "是否二级选课": "否",
        "实验信息": "",
        "重修是否占容量": "否",
        "是否选课时限制": "",
        "通识选修课组": ""
    },
    {
        "开课院系": "法学院",
        "课程号": "80662333",
        "课序号": "0",
        "课程名": "商标法与品牌管理",
        "学分": "3",
        "主讲教师": "冯术杰",
        "本科生课容量": "10",
        "本科生课余量": "10",
        "研究生课容量": "40",
        "研究生课余量": "40",
        "上课时间": "1-4(全周),1-3(全周)",
        "选课文字说明": "优先:法学院学生选课",
        "课程特色": "全外文授课",
        "年级": "",
        "是否二级选课": "否",
        "实验信息": "",
        "重修是否占容量": "否",
        "是否选课时限制": "",
        "通识选修课组": ""
    },
    {
        "开课院系": "法学院",
        "课程号": "80662343",
        "课序号": "0",
        "课程名": "知识产权与创意产业",
        "学分": "3",
        "主讲教师": "蒋舸",
        "本科生课容量": "10",
        "本科生课余量": "10",
        "研究生课容量": "40",
        "研究生课余量": "40",
        "上课时间": "4-2(全周)",
        "选课文字说明": "优先:法学院学生选课",
        "课程特色": "全外文授课",
        "年级": "",
        "是否二级选课": "否",
        "实验信息": "",
        "重修是否占容量": "否",
        "是否选课时限制": "",
        "通识选修课组": ""
    },
    {
        "开课院系": "法学院",
        "课程号": "80667012",
        "课序号": "0",
        "课程名": "婚姻家庭法",
        "学分": "2",
        "主讲教师": "龙俊",
        "本科生课容量": "10",
        "本科生课余量": "10",
        "研究生课容量": "100",
        "研究生课余量": "100",
        "上课时间": "2-6(全周)",
        "选课文字说明": "优先:法学院学生选课",
        "课程特色": "",
        "年级": "",
        "是否二级选课": "否",
        "实验信息": "",
        "重修是否占容量": "否",
        "是否选课时限制": "",
        "通识选修课组": ""
    },
    {
        "开课院系": "法学院",
        "课程号": "80669103",
        "课序号": "0",
        "课程名": "中国对外贸易和外商投资法",
        "学分": "3",
        "主讲教师": "MAHONY TARRANT MATTHEW",
        "本科生课容量": "0",
        "本科生课余量": "0",
        "研究生课容量": "30",
        "研究生课余量": "30",
        "上课时间": "4-2(前八周),3-2(前八周)",
        "选课文字说明": "限:法律硕士(JM)学生选课; 优先:留学生选课",
        "课程特色": "全外文授课",
        "年级": "",
        "是否二级选课": "否",
        "实验信息": "",
        "重修是否占容量": "否",
        "是否选课时限制": "是",
        "通识选修课组": ""
    },
    {
        "开课院系": "新闻学院",
        "课程号": "80670062",
        "课序号": "0",
        "课程名": "新闻与传播学前沿讲座",
        "学分": "2",
        "主讲教师": "史安斌",
        "本科生课容量": "0",
        "本科生课余量": "0",
        "研究生课容量": "55",
        "研究生课余量": "55",
        "上课时间": "5-6(1-11周)",
        "选课文字说明": "优先:新闻学院学生选课",
        "课程特色": "",
        "年级": "",
        "是否二级选课": "否",
        "实验信息": "",
        "重修是否占容量": "否",
        "是否选课时限制": "",
        "通识选修课组": ""
    },
    {
        "开课院系": "新闻学院",
        "课程号": "80670133",
        "课序号": "0",
        "课程名": "舆论传播研究",
        "学分": "3",
        "主讲教师": "陆洪磊",
        "本科生课容量": "0",
        "本科生课余量": "0",
        "研究生课容量": "30",
        "研究生课余量": "30",
        "上课时间": "4-6(全周)",
        "选课文字说明": "优先:新闻学院学生选课",
        "课程特色": "",
        "年级": "",
        "是否二级选课": "否",
        "实验信息": "",
        "重修是否占容量": "否",
        "是否选课时限制": "",
        "通识选修课组": ""
    },
    {
        "开课院系": "新闻学院",
        "课程号": "80670263",
        "课序号": "0",
        "课程名": "媒介经营管理研究",
        "学分": "3",
        "主讲教师": "崔保国",
        "本科生课容量": "0",
        "本科生课余量": "0",
        "研究生课容量": "25",
        "研究生课余量": "25",
        "上课时间": "2-2(全周)",
        "选课文字说明": "优先:新闻学院学生选课",
        "课程特色": "",
        "年级": "",
        "是否二级选课": "否",
        "实验信息": "",
        "重修是否占容量": "否",
        "是否选课时限制": "",
        "通识选修课组": ""
    },
    {
        "开课院系": "新闻学院",
        "课程号": "80670632",
        "课序号": "0",
        "课程名": "跨文化传播",
        "学分": "2",
        "主讲教师": "DUNHAM RICHARD SCOTT",
        "本科生课容量": "0",
        "本科生课余量": "0",
        "研究生课容量": "35",
        "研究生课余量": "35",
        "上课时间": "3-3(全周)",
        "选课文字说明": "优先:新闻学院学生选课",
        "课程特色": "全外文授课",
        "年级": "",
        "是否二级选课": "否",
        "实验信息": "",
        "重修是否占容量": "否",
        "是否选课时限制": "",
        "通识选修课组": ""
    },
    {
        "开课院系": "新闻学院",
        "课程号": "80670672",
        "课序号": "0",
        "课程名": "文化创意产业",
        "学分": "2",
        "主讲教师": "张铮",
        "本科生课容量": "0",
        "本科生课余量": "0",
        "研究生课容量": "25",
        "研究生课余量": "25",
        "上课时间": "5-3(1,4,8,10周),5-2(1,4,8,10周),5-1(1,4,8,10周),5-4(1,4,8,10周)",
        "选课文字说明": "限:新闻与传播专业学生选课",
        "课程特色": "",
        "年级": "",
        "是否二级选课": "否",
        "实验信息": "",
        "重修是否占容量": "否",
        "是否选课时限制": "是",
        "通识选修课组": ""
    }
]